pyopengltk/__init__.py
pyopengltk/base.py
pyopengltk/darwin.py
pyopengltk/linux.py
pyopengltk/opengl.py
pyopengltk/win32.py
pyopengltk-0.0.4.dist-info/LICENSE
pyopengltk-0.0.4.dist-info/METADATA
pyopengltk-0.0.4.dist-info/WHEEL
pyopengltk-0.0.4.dist-info/top_level.txt
pyopengltk-0.0.4.dist-info/RECORD
